{
	"info": {
		"_postman_id": "a993dbbc-c648-490d-96ff-1833b93d316e",
		"name": "api-ecom",
		"schema": "https://schema.getpostman.com/json/collection/v2.1.0/collection.json",
		"_exporter_id": "40803893"
	},
	"item": [
		{
			"name": "Categorias",
			"item": [
				{
					"name": "listado de categorias",
					"request": {
						"method": "GET",
						"header": [],
						"url": {
							"raw": "http://localhost:5219/api/Categories",
							"protocol": "http",
							"host": [
								"localhost"
							],
							"port": "5219",
							"path": [
								"api",
								"Categories"
							]
						}
					},
					"response": []
				},
				{
					"name": "obtener categorias",
					"request": {
						"method": "GET",
						"header": [],
						"url": {
							"raw": "http://localhost:5219/api/Categories/1",
							"protocol": "http",
							"host": [
								"localhost"
							],
							"port": "5219",
							"path": [
								"api",
								"Categories",
								"1"
							]
						}
					},
					"response": []
				},
				{
					"name": "Crear categorias",
					"request": {
						"method": "POST",
						"header": [],
						"body": {
							"mode": "raw",
							"raw": "{\r\n  \"name\": \"string\"\r\n}",
							"options": {
								"raw": {
									"language": "json"
								}
							}
						},
						"url": {
							"raw": "http://localhost:5219/api/Categories",
							"protocol": "http",
							"host": [
								"localhost"
							],
							"port": "5219",
							"path": [
								"api",
								"Categories"
							]
						}
					},
					"response": []
				},
				{
					"name": "Modificar categorias",
					"request": {
						"method": "PATCH",
						"header": [],
						"body": {
							"mode": "raw",
							"raw": "{\r\n  \"name\": \"string\"\r\n}",
							"options": {
								"raw": {
									"language": "json"
								}
							}
						},
						"url": {
							"raw": "http://localhost:5219/api/Categories/1",
							"protocol": "http",
							"host": [
								"localhost"
							],
							"port": "5219",
							"path": [
								"api",
								"Categories",
								"1"
							]
						}
					},
					"response": []
				},
				{
					"name": "Eliminar categoria",
					"request": {
						"method": "DELETE",
						"header": [],
						"body": {
							"mode": "raw",
							"raw": "",
							"options": {
								"raw": {
									"language": "json"
								}
							}
						},
						"url": {
							"raw": "http://localhost:5219/api/Categories/",
							"protocol": "http",
							"host": [
								"localhost"
							],
							"port": "5219",
							"path": [
								"api",
								"Categories",
								""
							]
						}
					},
					"response": []
				}
			]
		},
		{
			"name": "User",
			"item": [
				{
					"name": "registro usiario",
					"request": {
						"method": "POST",
						"header": [],
						"body": {
							"mode": "raw",
							"raw": "{\r\n  \"username\": \"DaniMrios\",\r\n  \"name\": \"daniel martin\",\r\n  \"password\": \"123456\",\r\n  \"role\": \"Admin\"\r\n}",
							"options": {
								"raw": {
									"language": "json"
								}
							}
						},
						"url": {
							"raw": "http://localhost:5219/api/Users",
							"protocol": "http",
							"host": [
								"localhost"
							],
							"port": "5219",
							"path": [
								"api",
								"Users"
							]
						}
					},
					"response": []
				},
				{
					"name": "login usuario",
					"request": {
						"method": "POST",
						"header": [],
						"body": {
							"mode": "raw",
							"raw": "{\r\n  \"username\": \"DaniMrios\",\r\n  \"name\": \"daniel martin\",\r\n  \"password\": \"123456\",\r\n  \"role\": \"Admin\"\r\n}",
							"options": {
								"raw": {
									"language": "json"
								}
							}
						},
						"url": {
							"raw": "http://localhost:5219/api/Users",
							"protocol": "http",
							"host": [
								"localhost"
							],
							"port": "5219",
							"path": [
								"api",
								"Users"
							]
						}
					},
					"response": []
				}
			]
		}
	]
}